{
    "summary": "Model: king99_pareto_modification\n        Computed from the raw b_i samples by multiplying by population and then getting\n        the proportion of the total pop (total pop=summed across all districts):\n        The posterior mean for the district-level voting preference of\n        guyanese_ACS_pct for hispanic_PL_pct is\n        0.477\n        The posterior mean for the district-level voting preference of\n        non-guyanese_ACS_pct for hispanic_PL_pct is\n        0.029\n        95% equal-tailed Bayesian credible interval for district-level voting preference of\n        guyanese_ACS_pct for hispanic_PL_pct is\n        [0.03069397 0.94197628]\n        95% equal-tailed Bayesian credible interval for district-level voting preference of\n        non-guyanese_ACS_pct for hispanic_PL_pct is\n        [0.02913448 0.02985099]\n        ",
    "posterior_mean_guyanese_ACS_pct_hispanic_PL_pct": 0.4773465137596804,
    "credible_interval_guyanese_ACS_pct_hispanic_PL_pct": [
        0.030693970715000365,
        0.9419762849583758
    ],
    "posterior_mean_NON_guyanese_ACS_pct_hispanic_PL_pct": 0.02949223372030788,
    "credible_interval_NON_guyanese_ACS_pct_hispanic_PL_pct": [
        0.0291344844454259,
        0.029850992700859866
    ]
}