{
    "summary": "Model: king99_pareto_modification\n        Computed from the raw b_i samples by multiplying by population and then getting\n        the proportion of the total pop (total pop=summed across all districts):\n        The posterior mean for the district-level voting preference of\n        belizean_ACS_pct for hispanic_PL_pct is\n        0.521\n        The posterior mean for the district-level voting preference of\n        non-belizean_ACS_pct for hispanic_PL_pct is\n        0.056\n        95% equal-tailed Bayesian credible interval for district-level voting preference of\n        belizean_ACS_pct for hispanic_PL_pct is\n        [0.332608   0.77629624]\n        95% equal-tailed Bayesian credible interval for district-level voting preference of\n        non-belizean_ACS_pct for hispanic_PL_pct is\n        [0.05562093 0.05589075]\n        ",
    "posterior_mean_belizean_ACS_pct_hispanic_PL_pct": 0.5210652567986428,
    "credible_interval_belizean_ACS_pct_hispanic_PL_pct": [
        0.3326080015520065,
        0.776296239663308
    ],
    "posterior_mean_NON_belizean_ACS_pct_hispanic_PL_pct": 0.05575802252663119,
    "credible_interval_NON_belizean_ACS_pct_hispanic_PL_pct": [
        0.055620928915695866,
        0.055890753443425874
    ]
}